ros2_fuzzer/__init__.py
ros2_fuzzer/process_handling.py
ros2_fuzzer/ros_basic_strategies.py
ros2_fuzzer/ros_commons.py
ros2_fuzzer/ros_fuzzer.py
ros2_fuzzer/test.py
ros2_fuzzer-1.0.0.dist-info/LICENSE
ros2_fuzzer-1.0.0.dist-info/METADATA
ros2_fuzzer-1.0.0.dist-info/WHEEL
ros2_fuzzer-1.0.0.dist-info/entry_points.txt
ros2_fuzzer-1.0.0.dist-info/top_level.txt
ros2_fuzzer-1.0.0.dist-info/RECORD
